CHANGES.rst
MANIFEST.in
setup.py
Products/__init__.py
Products.PloneHotfix20171128.egg-info/PKG-INFO
Products.PloneHotfix20171128.egg-info/SOURCES.txt
Products.PloneHotfix20171128.egg-info/dependency_links.txt
Products.PloneHotfix20171128.egg-info/entry_points.txt
Products.PloneHotfix20171128.egg-info/namespace_packages.txt
Products.PloneHotfix20171128.egg-info/not-zip-safe
Products.PloneHotfix20171128.egg-info/requires.txt
Products.PloneHotfix20171128.egg-info/top_level.txt
Products/PloneHotfix20171128/README.txt
Products/PloneHotfix20171128/__init__.py
Products/PloneHotfix20171128/in_portal.py
Products/PloneHotfix20171128/redirect.py
Products/PloneHotfix20171128/strformat.py
Products/PloneHotfix20171128/user_home_page.py
docs/LICENSE.GPL
docs/LICENSE.txt