Metadata-Version: 1.1
Name: Products.PloneHotfix20171128
Version: 1.0
Summary: Various Plone hotfixes, 2017-11-28
Home-page: https://github.com/plone
Author: Plone Security Team
Author-email: security@plone.org
License: GPL
Keywords: plone security hotfix patch
Platform: UNKNOWN
Classifier: Framework :: Plone
Classifier: Framework :: Plone :: 4.0
Classifier: Framework :: Plone :: 4.1
Classifier: Framework :: Plone :: 4.2
Classifier: Framework :: Plone :: 4.3
Classifier: Framework :: Plone :: 5.0
Classifier: Framework :: Plone :: 5.1
Classifier: Programming Language :: Python
Classifier: Programming Language :: Python :: 2.6
Classifier: Programming Language :: Python :: 2.7
